ciphergeard/__init__.py
ciphergeard/affine.py
ciphergeard/atbash.py
ciphergeard/baconion.py
ciphergeard/bifid.py
ciphergeard/caesar.py
ciphergeard/columnar_transposition.py
ciphergeard/morse.py
ciphergeard/playfair.py
ciphergeard/rail_fence.py
ciphergeard/rot13.py
ciphergeard/vernam.py
ciphergeard/vigenere/__init__.py
ciphergeard/vigenere/beaufort.py
ciphergeard/vigenere/gronsfeld.py
ciphergeard/vigenere/running_key.py
ciphergeard-1.0.dist-info/LICENSE
ciphergeard-1.0.dist-info/METADATA
ciphergeard-1.0.dist-info/WHEEL
ciphergeard-1.0.dist-info/top_level.txt
ciphergeard-1.0.dist-info/RECORD
