Metadata-Version: 2.1
Name: ciphergeard
Version: 1.0
Summary: Implementation of several famous ancient ciphers in Python.
Home-page: https://github.com/Evscion/Ciphergeard
Download-URL: https://github.com/Evscion/Ciphergeard/archive/refs/tags/v1.0.tar.gz
Author: Evscion
Author-email: ivoscev@gmail.com
Keywords: cipher,encoder
Classifier: Programming Language :: Python :: 3
Classifier: License :: OSI Approved :: MIT License
Classifier: Operating System :: OS Independent
Requires-Python: >=3.8
License-File: LICENSE
